MANIFEST.in
README.md
requirements-test.txt
requirements.txt
setup.py
Flask_CuddlyRest.egg-info/PKG-INFO
Flask_CuddlyRest.egg-info/SOURCES.txt
Flask_CuddlyRest.egg-info/dependency_links.txt
Flask_CuddlyRest.egg-info/not-zip-safe
Flask_CuddlyRest.egg-info/requires.txt
Flask_CuddlyRest.egg-info/top_level.txt
flask_cuddlyrest/__init__.py
flask_cuddlyrest/marshaller.py
flask_cuddlyrest/views.py
flask_cuddlyrest/ext/__init__.py
flask_cuddlyrest/ext/sphinxext.py
flask_cuddlyrest/ext/templates/service_definition.rst
test/__init__.py
test/test_marshaller.py