Metadata-Version: 1.1
Name: Flask-CuddlyRest
Version: 0.1.15
Summary: Flask restful API framework for MongoDB/MongoEngine
Home-page: http://github.com/wuurrd/flask-cuddlyrest
Author: David Buchmann
Author-email: david.buchmann@gmail.com
License: MIT
Platform: UNKNOWN
Classifier: Environment :: Web Environment
Classifier: Intended Audience :: Developers
Classifier: Operating System :: OS Independent
Classifier: Programming Language :: Python
Classifier: Topic :: Internet :: WWW/HTTP :: Dynamic Content
Classifier: Topic :: Software Development :: Libraries :: Python Modules
